pyrampl
