Metadata-Version: 2.1
Name: pyrampl
Version: 1.31
Summary: Python Random Access Machine programming language
Home-page: UNKNOWN
Author: Samy Zafrany
Author-email: sz@samyzaf.com
License: MIT
Keywords: random access machine simulation
Platform: UNKNOWN
